pyevtx.cp38-win32.pyd
libevtx_python-20251118.dist-info/COPYING
libevtx_python-20251118.dist-info/COPYING.LESSER
libevtx_python-20251118.dist-info/METADATA
libevtx_python-20251118.dist-info/WHEEL
libevtx_python-20251118.dist-info/top_level.txt
libevtx_python-20251118.dist-info/RECORD
