Metadata-Version: 2.1
Name: libevtx-python
Version: 20251118
Summary: Python bindings module for libevtx
Author: Joachim Metz
Author-email: joachim.metz@gmail.com
License: GNU Lesser General Public License v3 or later (LGPLv3+)
Classifier: Development Status :: 3 - Alpha
Classifier: Programming Language :: Python
Requires-Python: >=3.8
License-File: COPYING
License-File: COPYING.LESSER
